essexpropds/__init__.py
essexpropds/rent.py
essexpropds/util.py
essexpropds-0.0.4.dist-info/METADATA
essexpropds-0.0.4.dist-info/WHEEL
essexpropds-0.0.4.dist-info/top_level.txt
essexpropds-0.0.4.dist-info/RECORD
