Metadata-Version: 2.1
Name: essexpropds
Version: 0.0.4
Summary: A package for utils
Author: Jung Song
License: UNKNOWN
Platform: UNKNOWN
